{
  "schemaVersion": 1,
  "id": "auto-reauth",
  "version": "${version}",
  "name": "auto-reauth",
  "description": "",
  "authors": [],
  "contact": {
    "repo": "https://github.com/connorslade/auth-reauth"
  },
  "license": "All-Rights-Reserved",
  "environment": "client",
  "entrypoints": {
    "client": [
      "com.connorcode.authreauth.AutoReauth"
    ]
  },
  "mixins": [
    "auto-reauth.mixins.json"
  ],
  "depends": {
    "fabricloader": ">=${loader_version}",
    "fabric": "*",
    "minecraft": "${minecraft_version}"
  }
}
